embed_python_manager/__init__.py
embed_python_manager/downloader.py
embed_python_manager/env.py
embed_python_manager/manager.py
embed_python_manager/path_model.py
embed_python_manager/pip_suits.py
embed_python_manager/pyversion.py
embed_python_manager/source_list/npm_taobao_org.yml
embed_python_manager/source_list/www_python_org.yml
embed_python_manager/tk_suits.py
embed_python_manager-0.2.8.dist-info/LICENSE
embed_python_manager-0.2.8.dist-info/WHEEL
embed_python_manager-0.2.8.dist-info/METADATA
embed_python_manager-0.2.8.dist-info/RECORD
